Metadata-Version: 1.0
Name: shixiaolou
Version: 0.1
Summary: Factorial module.
Home-page: https://www.shiyanlou.com/courses/596
Author: ShiYanLou
Author-email: support@shiyanlou.com
License: MIT
Platform: Linux
